circuit_breaker_client/__init__.py
circuit_breaker_client/httpx_client.py
circuit_breaker_client/requests_session.py
circuit_breaker_client-0.1.0.dist-info/LICENSE
circuit_breaker_client-0.1.0.dist-info/METADATA
circuit_breaker_client-0.1.0.dist-info/WHEEL
circuit_breaker_client-0.1.0.dist-info/RECORD
