Metadata-Version: 2.3
Name: circuit-breaker-client
Version: 0.1.0
Summary: 
License: MIT
Author: daniel.perebinos@ebs-integrator.com
Author-email: daniel.perebinos@ebs-integrator.com
Requires-Python: >=3.13
Classifier: License :: OSI Approved :: MIT License
Classifier: Programming Language :: Python :: 3
Classifier: Programming Language :: Python :: 3.13
Provides-Extra: httpx
Provides-Extra: requests
Requires-Dist: httpx ; extra == "httpx"
Requires-Dist: requests ; extra == "requests"
Project-URL: Homepage, https://github.com/danielperebinos/circuit-breaker-client
Project-URL: Issues, https://github.com/danielperebinos/circuit-breaker-client/issues
